CHANGELOG.txt
LICENCE.txt
MANIFEST.in
README.txt
setup.py
QuangChinhTest.egg-info/PKG-INFO
QuangChinhTest.egg-info/SOURCES.txt
QuangChinhTest.egg-info/dependency_links.txt
QuangChinhTest.egg-info/top_level.txt
Test/__init__.py
venv/Lib/site-packages/_virtualenv.py
venv/Lib/site-packages/six.py
venv/Lib/site-packages/zipp.py
venv/Lib/site-packages/Pygments-2.12.0.dist-info/entry_points.txt
venv/Lib/site-packages/Pygments-2.12.0.dist-info/top_level.txt
venv/Lib/site-packages/_distutils_hack/__init__.py
venv/Lib/site-packages/_distutils_hack/override.py
venv/Lib/site-packages/bleach/__init__.py
venv/Lib/site-packages/bleach/callbacks.py
venv/Lib/site-packages/bleach/css_sanitizer.py
venv/Lib/site-packages/bleach/html5lib_shim.py
venv/Lib/site-packages/bleach/linkifier.py
venv/Lib/site-packages/bleach/parse_shim.py
venv/Lib/site-packages/bleach/sanitizer.py
venv/Lib/site-packages/bleach-5.0.1.dist-info/top_level.txt
venv/Lib/site-packages/bleach/_vendor/__init__.py
venv/Lib/site-packages/bleach/_vendor/parse.py
venv/Lib/site-packages/bleach/_vendor/vendor.txt
venv/Lib/site-packages/bleach/_vendor/html5lib/__init__.py
venv/Lib/site-packages/bleach/_vendor/html5lib/_ihatexml.py
venv/Lib/site-packages/bleach/_vendor/html5lib/_inputstream.py
venv/Lib/site-packages/bleach/_vendor/html5lib/_tokenizer.py
venv/Lib/site-packages/bleach/_vendor/html5lib/_utils.py
venv/Lib/site-packages/bleach/_vendor/html5lib/constants.py
venv/Lib/site-packages/bleach/_vendor/html5lib/html5parser.py
venv/Lib/site-packages/bleach/_vendor/html5lib/serializer.py
venv/Lib/site-packages/bleach/_vendor/html5lib-1.1.dist-info/top_level.txt
venv/Lib/site-packages/bleach/_vendor/html5lib/_trie/__init__.py
venv/Lib/site-packages/bleach/_vendor/html5lib/_trie/_base.py
venv/Lib/site-packages/bleach/_vendor/html5lib/_trie/py.py
venv/Lib/site-packages/bleach/_vendor/html5lib/filters/__init__.py
venv/Lib/site-packages/bleach/_vendor/html5lib/filters/alphabeticalattributes.py
venv/Lib/site-packages/bleach/_vendor/html5lib/filters/base.py
venv/Lib/site-packages/bleach/_vendor/html5lib/filters/inject_meta_charset.py
venv/Lib/site-packages/bleach/_vendor/html5lib/filters/lint.py
venv/Lib/site-packages/bleach/_vendor/html5lib/filters/optionaltags.py
venv/Lib/site-packages/bleach/_vendor/html5lib/filters/sanitizer.py
venv/Lib/site-packages/bleach/_vendor/html5lib/filters/whitespace.py
venv/Lib/site-packages/certifi-2022.6.15.dist-info/top_level.txt
venv/Lib/site-packages/charset_normalizer-2.1.0.dist-info/entry_points.txt
venv/Lib/site-packages/charset_normalizer-2.1.0.dist-info/top_level.txt
venv/Lib/site-packages/commonmark-0.9.1.dist-info/entry_points.txt
venv/Lib/site-packages/commonmark-0.9.1.dist-info/top_level.txt
venv/Lib/site-packages/docutils-0.19.dist-info/COPYING.txt
venv/Lib/site-packages/docutils-0.19.dist-info/entry_points.txt
venv/Lib/site-packages/docutils-0.19.dist-info/top_level.txt
venv/Lib/site-packages/idna-3.3.dist-info/top_level.txt
venv/Lib/site-packages/importlib_metadata-4.12.0.dist-info/top_level.txt
venv/Lib/site-packages/keyring-23.7.0.dist-info/entry_points.txt
venv/Lib/site-packages/keyring-23.7.0.dist-info/top_level.txt
venv/Lib/site-packages/pip-21.3.1.dist-info/LICENSE.txt
venv/Lib/site-packages/pip-21.3.1.dist-info/entry_points.txt
venv/Lib/site-packages/pip-21.3.1.dist-info/top_level.txt
venv/Lib/site-packages/pkginfo-1.8.3.dist-info/LICENSE.txt
venv/Lib/site-packages/pkginfo-1.8.3.dist-info/entry_points.txt
venv/Lib/site-packages/pkginfo-1.8.3.dist-info/top_level.txt
venv/Lib/site-packages/pypirc-1.0.4.dist-info/entry_points.txt
venv/Lib/site-packages/pypirc-1.0.4.dist-info/top_level.txt
venv/Lib/site-packages/pypirc3-1.1.0.dist-info/LICENSE.txt
venv/Lib/site-packages/pypirc3-1.1.0.dist-info/entry_points.txt
venv/Lib/site-packages/pypirc3-1.1.0.dist-info/top_level.txt
venv/Lib/site-packages/pywin32_ctypes-0.2.0.dist-info/LICENSE.txt
venv/Lib/site-packages/pywin32_ctypes-0.2.0.dist-info/top_level.txt
venv/Lib/site-packages/readme_renderer-35.0.dist-info/top_level.txt
venv/Lib/site-packages/requests-2.28.1.dist-info/top_level.txt
venv/Lib/site-packages/requests_toolbelt-0.9.1.dist-info/top_level.txt
venv/Lib/site-packages/rfc3986-2.0.0.dist-info/top_level.txt
venv/Lib/site-packages/setuptools-60.2.0.dist-info/entry_points.txt
venv/Lib/site-packages/setuptools-60.2.0.dist-info/top_level.txt
venv/Lib/site-packages/six-1.16.0.dist-info/top_level.txt
venv/Lib/site-packages/twine-4.0.1.dist-info/entry_points.txt
venv/Lib/site-packages/twine-4.0.1.dist-info/top_level.txt
venv/Lib/site-packages/urllib3-1.26.11.dist-info/LICENSE.txt
venv/Lib/site-packages/urllib3-1.26.11.dist-info/top_level.txt
venv/Lib/site-packages/webencodings-0.5.1.dist-info/top_level.txt
venv/Lib/site-packages/wheel-0.37.1.dist-info/LICENSE.txt
venv/Lib/site-packages/wheel-0.37.1.dist-info/entry_points.txt
venv/Lib/site-packages/wheel-0.37.1.dist-info/top_level.txt
venv/Lib/site-packages/zipp-3.8.1.dist-info/top_level.txt
