Metadata-Version: 2.1
Name: QuangChinhTest
Version: 0.0.1
Summary: A very basic
Home-page: UNKNOWN
Author: Quang Chinh
Author-email: quangchinh222000@gmail.com
License: MIT
Keywords: test
Platform: UNKNOWN
Classifier: Development Status :: 5 - Production/Stable
Classifier: Intended Audience :: Education
Classifier: Operating System :: Microsoft :: Windows :: Windows 10
Classifier: License :: OSI Approved :: MIT License
Classifier: Programming Language :: Python :: 3
License-File: LICENCE.txt
